{
  "product_id": "cornetto_green_grape_yogurt",
  "productName": "可爱多甜筒 青提酸奶口味冰淇淋",
  "brand": "和路雪（Wall's）",
  "category": "冰淇淋",
  "video_id": "fmcg-2",
  "dimensions": [
    {
      "dimension_id": "D1",
      "features": [
        {
          "id": "f1",
          "name": "青提+酸奶双层次风味",
          "fact": "上层浓郁酸奶冰淇淋，下层清爽青提雪泥，一支两种口感交替。",
          "claim": "一支吃出两种夏天",
          "scores": {
            "P1": 0.15,
            "P2": 0.10,
            "P3": 0.55,
            "P4": 0.90,
            "P5": 0.05,
            "P6": 0.20,
            "P7": 0.25
          }
        },
        {
          "id": "f2",
          "name": "顶部奶酪曲奇碎 + 底部巧克力尖",
          "fact": "甜筒顶部撒奶酪曲奇饼干碎，底部保留浓郁巧克力尖，首尾各有惊喜。",
          "claim": "从第一口好吃到最后一口",
          "scores": {
            "P1": 0.30,
            "P2": 0.05,
            "P3": 0.40,
            "P4": 0.95,
            "P5": 0.05,
            "P6": 0.25,
            "P7": 0.15
          }
        },
        {
          "id": "f3",
          "name": "乳酸菌+真实果汁配料",
          "fact": "添加乳酸菌饮料和浓缩苹果汁，减少添加剂感，配料表更贴近天然。",
          "claim": "吃冰淇淋也能有轻盈感",
          "scores": {
            "P1": 0.60,
            "P2": 0.05,
            "P3": 0.30,
            "P4": 0.50,
            "P5": 0.55,
            "P6": 0.35,
            "P7": 0.40
          }
        },
        {
          "id": "f4",
          "name": "和路雪灯塔工厂制造",
          "fact": "生产于太仓灯塔工厂，代表数字化与可持续制造标准，品质一致性有保障。",
          "claim": "每一支都一样的干净",
          "scores": {
            "P1": 0.82,
            "P2": 0.10,
            "P3": 0.25,
            "P4": 0.10,
            "P5": 0.65,
            "P6": 0.30,
            "P7": 0.45
          }
        }
      ]
    }
  ]
}
